{
    "personen": {
        "person": {
            "Willi": {
                "vorname": "Willi",
                "nachname": "Oberh\u00e4sli",
                "email": "",
                "telefon": "",
                "tag": "",
                "monat": "",
                "jahr": "",
                "stunde": "",
                "minute": "",
                "stadt": ""
            },
            "Alice": {
                "vorname": "Alice",
                "nachname": "",
                "email": "",
                "telefon": "",
                "tag": "",
                "monat": "",
                "jahr": "",
                "stunde": "",
                "minute": "",
                "stadt": ""
            },
            "dfdfd": {
                "vorname": "dfdfd",
                "nachname": "",
                "email": "",
                "telefon": "",
                "tag": "",
                "monat": "",
                "jahr": "",
                "stunde": "",
                "minute": "",
                "stadt": ""
            },
            "jkdfljl@hotmail.com": {
                "vorname": "Fabio",
                "nachname": "Willi",
                "email": "jkdfljl@hotmail.com",
                "telefon": "0786645559",
                "tag": "",
                "monat": "",
                "jahr": "",
                "stunde": "",
                "minute": "",
                "stadt": "Schwende"
            },
            "willi.oberhaensli@hotmail.com": {
                "vorname": "Willi",
                "nachname": "Oberh\u00e4nsli",
                "email": "willi.oberhaensli@hotmail.com",
                "telefon": "0786645558",
                "tag": "",
                "monat": "",
                "jahr": "",
                "stunde": "",
                "minute": "",
                "stadt": "Schwende"
            },
            "": {
                "vorname": "Willi",
                "nachname": "Oberhaensli",
                "email": "",
                "telefon": "",
                "tag": "",
                "monat": "",
                "jahr": "",
                "stunde": "",
                "minute": "",
                "stadt": ""
            },
            "Oberh\u00e4n": {
                "vorname": "",
                "nachname": "Willi",
                "email": "Oberh\u00e4n",
                "telefon": "dfkfd",
                "tag": "kfdljd",
                "monat": "",
                "jahr": "",
                "stunde": "",
                "minute": "",
                "stadt": ""
            },
            "olivia.sutter@gmail.com": {
                "vorname": "Olivia",
                "nachname": "Sutter",
                "email": "olivia.sutter@gmail.com",
                "telefon": "089778894849",
                "tag": "08",
                "monat": "10",
                "jahr": "1994",
                "stunde": "09",
                "minute": "39",
                "stadt": "2001"
            }
        }
    }
}